histr.py
histr-0.0.1.dist-info/LICENSE
histr-0.0.1.dist-info/METADATA
histr-0.0.1.dist-info/WHEEL
histr-0.0.1.dist-info/top_level.txt
histr-0.0.1.dist-info/RECORD
