Metadata-Version: 2.1
Name: histr
Version: 0.0.1
Summary: One stop solution for text preprocessing on devanagari text
Home-page: https://github.com/amankhandelia/histr
Author: Aman Khandelia
Author-email: opensourceaman@gmail.com
License: MIT License
Requires-Python: >3.5
License-File: LICENSE
